strands_tools_community/__init__.py
strands_tools_community/deepgram.py
strands_tools_community/hubspot.py
strands_tools_community/teams.py
strands_tools_community/templates/__init__.py
strands_tools_community/templates/hubspot_examples.py
strands_tools_community/templates/teams_templates.py
strands_tools_community-0.2.0.dist-info/licenses/LICENSE
strands_tools_community-0.2.0.dist-info/METADATA
strands_tools_community-0.2.0.dist-info/WHEEL
strands_tools_community-0.2.0.dist-info/top_level.txt
strands_tools_community-0.2.0.dist-info/RECORD
