Metadata-Version: 2.4
Name: strands-tools-community
Version: 0.2.0
Summary: Meta-package for Strands community tools (convenience wrapper for strands-deepgram, strands-hubspot, strands-teams)
Home-page: https://github.com/eraykeskinmac/strands-tools-community
Author: Eray Keskin
Author-email: Eray Keskin <eraykeskinmac@gmail.com>
License: MIT
Project-URL: Homepage, https://github.com/eraykeskinmac/strands-tools-community
Project-URL: Documentation, https://github.com/eraykeskinmac/strands-tools-community
Project-URL: Repository, https://github.com/eraykeskinmac/strands-tools-community
Project-URL: Bug Reports, https://github.com/eraykeskinmac/strands-tools-community/issues
Keywords: strands,ai,agents,deepgram,hubspot,teams,speech-to-text,crm,adaptive-cards,meta-package
Classifier: Development Status :: 4 - Beta
Classifier: Intended Audience :: Developers
Classifier: License :: OSI Approved :: MIT License
Classifier: Programming Language :: Python :: 3
Classifier: Programming Language :: Python :: 3.9
Classifier: Programming Language :: Python :: 3.10
Classifier: Programming Language :: Python :: 3.11
Classifier: Programming Language :: Python :: 3.12
Classifier: Topic :: Software Development :: Libraries :: Python Modules
Classifier: Topic :: Scientific/Engineering :: Artificial Intelligence
Requires-Python: >=3.9
License-File: LICENSE
Requires-Dist: strands-agents>=1.11.0
Requires-Dist: strands-deepgram>=0.1.0
Requires-Dist: strands-hubspot>=0.1.0
Requires-Dist: strands-teams>=0.1.0
Provides-Extra: dev
Requires-Dist: pytest>=7.0.0; extra == "dev"
Requires-Dist: black>=23.0.0; extra == "dev"
Requires-Dist: flake8>=6.0.0; extra == "dev"
Requires-Dist: mypy>=1.0.0; extra == "dev"
Provides-Extra: demo
Requires-Dist: prompt-toolkit>=3.0.0; extra == "demo"
Requires-Dist: halo>=0.0.31; extra == "demo"
Requires-Dist: colorama>=0.4.6; extra == "demo"
Dynamic: author
Dynamic: home-page
Dynamic: license-file
Dynamic: requires-python
